README.md
setup.cfg
setup.py
pyyaxml/__init__.py
pyyaxml/example.py
pyyaxml/search.py
pyyaxml.egg-info/PKG-INFO
pyyaxml.egg-info/SOURCES.txt
pyyaxml.egg-info/dependency_links.txt
pyyaxml.egg-info/not-zip-safe
pyyaxml.egg-info/requires.txt
pyyaxml.egg-info/top_level.txt