Metadata-Version: 1.0
Name: pyyaxml
Version: 0.6.0
Summary: Python API to Yandex.XML
Home-page: https://github.com/dbf256/py-ya-xml
Author: Alexey Moskvin
Author-email: dbf256@gmail.com
License: MIT
Platform: UNKNOWN
